fftvis/__init__.py
fftvis/cli.py
fftvis/logutils.py
fftvis/utils.py
fftvis/wrapper.py
fftvis/core/__init__.py
fftvis/core/antenna_gridding.py
fftvis/core/beams.py
fftvis/core/simulate.py
fftvis/core/utils.py
fftvis/cpu/__init__.py
fftvis/cpu/beams.py
fftvis/cpu/cpu_simulate.py
fftvis/cpu/nufft.py
fftvis/cpu/utils.py
fftvis/gpu/__init__.py
fftvis/gpu/beams.py
fftvis/gpu/gpu_simulate.py
fftvis/gpu/nufft.py
fftvis/gpu/utils.py
fftvis-1.0.0.dist-info/licenses/LICENSE
fftvis-1.0.0.dist-info/METADATA
fftvis-1.0.0.dist-info/WHEEL
fftvis-1.0.0.dist-info/entry_points.txt
fftvis-1.0.0.dist-info/top_level.txt
fftvis-1.0.0.dist-info/RECORD
