Metadata-Version: 2.4
Name: fftvis
Version: 1.0.0
Summary: An FFT-based visibility simulator
Author-email: Tyler Cox <tyler.a.cox@berkeley.edu>, Steven Murray <steven.murray@sns.it>
License: MIT
Classifier: Development Status :: 3 - Alpha
Classifier: Intended Audience :: Developers
Classifier: Intended Audience :: Science/Research
Classifier: License :: OSI Approved :: MIT License
Classifier: Operating System :: POSIX
Classifier: Operating System :: Unix
Classifier: Programming Language :: Python
Classifier: Programming Language :: Python :: 3
Classifier: Programming Language :: Python :: 3 :: Only
Classifier: Programming Language :: Python :: Implementation :: CPython
Classifier: Topic :: Scientific/Engineering
Classifier: Topic :: Scientific/Engineering :: Mathematics
Classifier: Topic :: Scientific/Engineering :: Visualization
Requires-Python: >=3.9
License-File: LICENSE
Requires-Dist: numpy
Requires-Dist: matvis>=1.3.2
Requires-Dist: finufft
Requires-Dist: pyuvdata>=3.1.2
Requires-Dist: psutil
Requires-Dist: typer
Requires-Dist: rich
Requires-Dist: ray
Requires-Dist: threadpoolctl
Requires-Dist: numba
Requires-Dist: memray
Provides-Extra: dev
Requires-Dist: mpi4py; extra == "dev"
Requires-Dist: pytest; extra == "dev"
Requires-Dist: pre-commit; extra == "dev"
Requires-Dist: pytest-cov; extra == "dev"
Requires-Dist: pytest-xdist; extra == "dev"
Requires-Dist: pyradiosky; extra == "dev"
Requires-Dist: pyuvsim[sim]; extra == "dev"
Requires-Dist: hera_sim; extra == "dev"
Dynamic: license-file
